{
  "status": "ok",
  "model": "MS-GSE + RPF",
  "variant": "full",
  "runs": [
    {
      "status": "ok",
      "dataset": "cmapss",
      "target": "degradation_stage_id",
      "task": "cmapss_degradation_stage_classification",
      "variant": "full",
      "seed": 42,
      "protocol": "ready_csv_causal_windows_same_backbone",
      "split_protocol": "official_test_grouped_unit_validation",
      "validation_group_cols": [
        "subset",
        "unit"
      ],
      "n_rows_total": 265256,
      "n_features": 25,
      "window_size": 32,
      "train_size": 1200,
      "val_size": 1200,
      "test_size": 1200,
      "class_id_mapping": {
        "0": 0,
        "1": 1,
        "2": 2
      },
      "class_distribution_total": {
        "0": 140206,
        "1": 91625,
        "2": 33425
      },
      "evidence_prior": {
        "enabled": false,
        "mode": "none",
        "matched_edges": 0
      },
      "task_salience": {
        "enabled": false
      },
      "val_metrics": {
        "accuracy": 0.38416666666666666,
        "balanced_accuracy": 0.3841666666666666,
        "macro_f1": 0.3748852975958136,
        "macro_precision": 0.3751704700211415,
        "macro_recall": 0.3841666666666666,
        "positive_f1": 0.3748852975958136,
        "positive_precision": 0.3751704700211415,
        "positive_recall": 0.3841666666666666,
        "ordinal_mae": 0.8108333333333333,
        "within_one_stage_accuracy": 0.805
      },
      "test_metrics": {
        "accuracy": 0.36833333333333335,
        "balanced_accuracy": 0.36833333333333335,
        "macro_f1": 0.36030776816999016,
        "macro_precision": 0.36267909199255716,
        "macro_recall": 0.36833333333333335,
        "positive_f1": 0.36030776816999016,
        "positive_precision": 0.36267909199255716,
        "positive_recall": 0.36833333333333335,
        "ordinal_mae": 0.8408333333333333,
        "within_one_stage_accuracy": 0.7908333333333334
      },
      "positive_threshold": null,
      "thresholded_val_metrics": null,
      "thresholded_test_metrics": null,
      "primary_test_metrics": {
        "accuracy": 0.36833333333333335,
        "balanced_accuracy": 0.36833333333333335,
        "macro_f1": 0.36030776816999016,
        "macro_precision": 0.36267909199255716,
        "macro_recall": 0.36833333333333335,
        "positive_f1": 0.36030776816999016,
        "positive_precision": 0.36267909199255716,
        "positive_recall": 0.36833333333333335,
        "ordinal_mae": 0.8408333333333333,
        "within_one_stage_accuracy": 0.7908333333333334
      },
      "efficiency": {
        "parameters": 13212,
        "train_seconds": 2.3742315999697894,
        "train_samples_per_second": 1010.8533641075868,
        "ordinal_loss_weight": 0.0,
        "path_entropy_weight": 0.0,
        "path_aux_weight": 0.0,
        "health_aux_weight": 0.1,
        "val_health_mae": 0.3416566252708435,
        "test_health_mae": 0.328254759311676,
        "test_inference_seconds": 0.4121208998840302,
        "test_inference_samples_per_second": 2911.766911936951
      },
      "path_budget": {
        "requested_max_paths": 16,
        "actual_max_paths": 16,
        "auto_path_budget": false,
        "n_feature_groups": 25,
        "path_coverage_mode": "target_group",
        "coverage_dedup_mode": "soft",
        "coverage_redundancy_penalty": 0.05,
        "ordinal_loss_weight": 0.0,
        "path_entropy_weight": 0.0,
        "path_aux_weight": 0.0,
        "health_aux_weight": 0.1,
        "health_rul_cap": 125.0,
        "health_aux_enabled": true,
        "use_task_salience": false,
        "salience_mode": "class",
        "lifecycle_salience_weight": 0.5,
        "order_anchor_evidence_weight": 0.35,
        "algorithmic_evidence_top_k": 0,
        "salience_selection_strength": 0.0,
        "use_temporal_descriptors": false,
        "temporal_descriptor_weight": 0.5,
        "use_multihop_paths": false,
        "multihop_path_fraction": 0.25,
        "use_context_router": true,
        "protect_order_anchor_target": false,
        "protect_order_anchor_path_nodes": false,
        "protected_order_anchor": null
      },
      "top_evidence_paths": [
        {
          "source_index": 9,
          "bridge_index": -1,
          "target_index": 19,
          "count": 3,
          "mean_weight": 0.18262328207492828,
          "mean_reliability": 0.4526263276735942,
          "mean_edge_weight": 0.2800520559151967,
          "mean_prior_weight": 0.0,
          "mean_salience_weight": 0.0,
          "mean_hop_count": 1.0,
          "source": "sensor_06",
          "bridge": "",
          "target": "sensor_16",
          "path": "sensor_06 -> sensor_16",
          "group_path": "sensor_06 -> sensor_16"
        },
        {
          "source_index": 23,
          "bridge_index": -1,
          "target_index": 10,
          "count": 44,
          "mean_weight": 0.17825613949786534,
          "mean_reliability": 0.4455712308937853,
          "mean_edge_weight": 0.2906307117505507,
          "mean_prior_weight": 0.0,
          "mean_salience_weight": 0.0,
          "mean_hop_count": 1.0,
          "source": "sensor_20",
          "bridge": "",
          "target": "sensor_07",
          "path": "sensor_20 -> sensor_07",
          "group_path": "sensor_20 -> sensor_07"
        },
        {
          "source_index": 9,
          "bridge_index": -1,
          "target_index": 5,
          "count": 3,
          "mean_weight": 0.1711154282093048,
          "mean_reliability": 0.5141777197519938,
          "mean_edge_weight": 0.27800490458806354,
          "mean_prior_weight": 0.0,
          "mean_salience_weight": 0.0,
          "mean_hop_count": 1.0,
          "source": "sensor_06",
          "bridge": "",
          "target": "sensor_02",
          "path": "sensor_06 -> sensor_02",
          "group_path": "sensor_06 -> sensor_02"
        },
        {
          "source_index": 21,
          "bridge_index": -1,
          "target_index": 3,
          "count": 6,
          "mean_weight": 0.17068123817443848,
          "mean_reliability": 0.44935692350069684,
          "mean_edge_weight": 0.2913238803545634,
          "mean_prior_weight": 0.0,
          "mean_salience_weight": 0.0,
          "mean_hop_count": 1.0,
          "source": "sensor_18",
          "bridge": "",
          "target": "op_setting_3",
          "path": "sensor_18 -> op_setting_3",
          "group_path": "sensor_18 -> op_setting_3"
        },
        {
          "source_index": 23,
          "bridge_index": -1,
          "target_index": 9,
          "count": 5,
          "mean_weight": 0.16684336066246033,
          "mean_reliability": 0.4605145394802094,
          "mean_edge_weight": 0.2850085198879242,
          "mean_prior_weight": 0.0,
          "mean_salience_weight": 0.0,
          "mean_hop_count": 1.0,
          "source": "sensor_20",
          "bridge": "",
          "target": "sensor_06",
          "path": "sensor_20 -> sensor_06",
          "group_path": "sensor_20 -> sensor_06"
        },
        {
          "source_index": 5,
          "bridge_index": -1,
          "target_index": 6,
          "count": 6,
          "mean_weight": 0.16567096362511316,
          "mean_reliability": 0.45753232141335803,
          "mean_edge_weight": 0.29410530130068463,
          "mean_prior_weight": 0.0,
          "mean_salience_weight": 0.0,
          "mean_hop_count": 1.0,
          "source": "sensor_02",
          "bridge": "",
          "target": "sensor_03",
          "path": "sensor_02 -> sensor_03",
          "group_path": "sensor_02 -> sensor_03"
        },
        {
          "source_index": 23,
          "bridge_index": -1,
          "target_index": 5,
          "count": 2,
          "mean_weight": 0.16064967215061188,
          "mean_reliability": 0.45275481045246124,
          "mean_edge_weight": 0.2951347976922989,
          "mean_prior_weight": 0.0,
          "mean_salience_weight": 0.0,
          "mean_hop_count": 1.0,
          "source": "sensor_20",
          "bridge": "",
          "target": "sensor_02",
          "path": "sensor_20 -> sensor_02",
          "group_path": "sensor_20 -> sensor_02"
        },
        {
          "source_index": 17,
          "bridge_index": -1,
          "target_index": 19,
          "count": 24,
          "mean_weight": 0.15906824745858708,
          "mean_reliability": 0.4604141252736251,
          "mean_edge_weight": 0.2976248028377692,
          "mean_prior_weight": 0.0,
          "mean_salience_weight": 0.0,
          "mean_hop_count": 1.0,
          "source": "sensor_14",
          "bridge": "",
          "target": "sensor_16",
          "path": "sensor_14 -> sensor_16",
          "group_path": "sensor_14 -> sensor_16"
        },
        {
          "source_index": 20,
          "bridge_index": -1,
          "target_index": 1,
          "count": 2,
          "mean_weight": 0.15677735209465027,
          "mean_reliability": 0.459836944937706,
          "mean_edge_weight": 0.2785436064004898,
          "mean_prior_weight": 0.0,
          "mean_salience_weight": 0.0,
          "mean_hop_count": 1.0,
          "source": "sensor_17",
          "bridge": "",
          "target": "op_setting_1",
          "path": "sensor_17 -> op_setting_1",
          "group_path": "sensor_17 -> op_setting_1"
        },
        {
          "source_index": 7,
          "bridge_index": -1,
          "target_index": 0,
          "count": 1,
          "mean_weight": 0.15427540242671967,
          "mean_reliability": 0.47412818670272827,
          "mean_edge_weight": 0.28642722964286804,
          "mean_prior_weight": 0.0,
          "mean_salience_weight": 0.0,
          "mean_hop_count": 1.0,
          "source": "sensor_04",
          "bridge": "",
          "target": "cycle",
          "path": "sensor_04 -> cycle",
          "group_path": "sensor_04 -> cycle"
        },
        {
          "source_index": 17,
          "bridge_index": -1,
          "target_index": 14,
          "count": 1,
          "mean_weight": 0.15354792773723602,
          "mean_reliability": 0.4335719645023346,
          "mean_edge_weight": 0.2804235816001892,
          "mean_prior_weight": 0.0,
          "mean_salience_weight": 0.0,
          "mean_hop_count": 1.0,
          "source": "sensor_14",
          "bridge": "",
          "target": "sensor_11",
          "path": "sensor_14 -> sensor_11",
          "group_path": "sensor_14 -> sensor_11"
        },
        {
          "source_index": 2,
          "bridge_index": -1,
          "target_index": 11,
          "count": 2,
          "mean_weight": 0.15051710605621338,
          "mean_reliability": 0.4270080626010895,
          "mean_edge_weight": 0.27838510274887085,
          "mean_prior_weight": 0.0,
          "mean_salience_weight": 0.0,
          "mean_hop_count": 1.0,
          "source": "op_setting_2",
          "bridge": "",
          "target": "sensor_08",
          "path": "op_setting_2 -> sensor_08",
          "group_path": "op_setting_2 -> sensor_08"
        },
        {
          "source_index": 5,
          "bridge_index": -1,
          "target_index": 19,
          "count": 65,
          "mean_weight": 0.14887185606818934,
          "mean_reliability": 0.46516613272520213,
          "mean_edge_weight": 0.2984238106470842,
          "mean_prior_weight": 0.0,
          "mean_salience_weight": 0.0,
          "mean_hop_count": 1.0,
          "source": "sensor_02",
          "bridge": "",
          "target": "sensor_16",
          "path": "sensor_02 -> sensor_16",
          "group_path": "sensor_02 -> sensor_16"
        },
        {
          "source_index": 15,
          "bridge_index": -1,
          "target_index": 14,
          "count": 41,
          "mean_weight": 0.14342841396971448,
          "mean_reliability": 0.46675488352775574,
          "mean_edge_weight": 0.28178669475927587,
          "mean_prior_weight": 0.0,
          "mean_salience_weight": 0.0,
          "mean_hop_count": 1.0,
          "source": "sensor_12",
          "bridge": "",
          "target": "sensor_11",
          "path": "sensor_12 -> sensor_11",
          "group_path": "sensor_12 -> sensor_11"
        },
        {
          "source_index": 23,
          "bridge_index": -1,
          "target_index": 22,
          "count": 3,
          "mean_weight": 0.14150024205446243,
          "mean_reliability": 0.46407904227574664,
          "mean_edge_weight": 0.2892336845397949,
          "mean_prior_weight": 0.0,
          "mean_salience_weight": 0.0,
          "mean_hop_count": 1.0,
          "source": "sensor_20",
          "bridge": "",
          "target": "sensor_19",
          "path": "sensor_20 -> sensor_19",
          "group_path": "sensor_20 -> sensor_19"
        },
        {
          "source_index": 8,
          "bridge_index": -1,
          "target_index": 4,
          "count": 2,
          "mean_weight": 0.1397825889289379,
          "mean_reliability": 0.44882941246032715,
          "mean_edge_weight": 0.2745770514011383,
          "mean_prior_weight": 0.0,
          "mean_salience_weight": 0.0,
          "mean_hop_count": 1.0,
          "source": "sensor_05",
          "bridge": "",
          "target": "sensor_01",
          "path": "sensor_05 -> sensor_01",
          "group_path": "sensor_05 -> sensor_01"
        },
        {
          "source_index": 24,
          "bridge_index": -1,
          "target_index": 3,
          "count": 3,
          "mean_weight": 0.1366856520374616,
          "mean_reliability": 0.4843027393023173,
          "mean_edge_weight": 0.27746695280075073,
          "mean_prior_weight": 0.0,
          "mean_salience_weight": 0.0,
          "mean_hop_count": 1.0,
          "source": "sensor_21",
          "bridge": "",
          "target": "op_setting_3",
          "path": "sensor_21 -> op_setting_3",
          "group_path": "sensor_21 -> op_setting_3"
        },
        {
          "source_index": 23,
          "bridge_index": -1,
          "target_index": 21,
          "count": 3,
          "mean_weight": 0.13642310599486032,
          "mean_reliability": 0.45872921744982403,
          "mean_edge_weight": 0.28797751665115356,
          "mean_prior_weight": 0.0,
          "mean_salience_weight": 0.0,
          "mean_hop_count": 1.0,
          "source": "sensor_20",
          "bridge": "",
          "target": "sensor_18",
          "path": "sensor_20 -> sensor_18",
          "group_path": "sensor_20 -> sensor_18"
        },
        {
          "source_index": 8,
          "bridge_index": -1,
          "target_index": 5,
          "count": 1,
          "mean_weight": 0.13592903316020966,
          "mean_reliability": 0.4704394042491913,
          "mean_edge_weight": 0.28705915808677673,
          "mean_prior_weight": 0.0,
          "mean_salience_weight": 0.0,
          "mean_hop_count": 1.0,
          "source": "sensor_05",
          "bridge": "",
          "target": "sensor_02",
          "path": "sensor_05 -> sensor_02",
          "group_path": "sensor_05 -> sensor_02"
        },
        {
          "source_index": 20,
          "bridge_index": -1,
          "target_index": 9,
          "count": 119,
          "mean_weight": 0.13138423601807164,
          "mean_reliability": 0.46802740011896404,
          "mean_edge_weight": 0.29183554849704774,
          "mean_prior_weight": 0.0,
          "mean_salience_weight": 0.0,
          "mean_hop_count": 1.0,
          "source": "sensor_17",
          "bridge": "",
          "target": "sensor_06",
          "path": "sensor_17 -> sensor_06",
          "group_path": "sensor_17 -> sensor_06"
        }
      ],
      "diagnostics": {
        "model_family": "ms_gse_rpf",
        "parameters": 13212,
        "epochs": 2,
        "batch_size": 128,
        "loss_tail": [
          1.1334178686141967,
          1.1194265604019165
        ],
        "val_macro_f1_history_tail": [
          0.3748852975958136,
          0.36777307106208673
        ],
        "best_val_macro_f1": 0.3748852975958136,
        "train_seconds": 2.3742315999697894,
        "train_samples_per_second": 1010.8533641075868,
        "ordinal_loss_weight": 0.0,
        "path_entropy_weight": 0.0,
        "path_aux_weight": 0.0,
        "health_aux_weight": 0.1,
        "val_health_mae": 0.3416566252708435,
        "test_health_mae": 0.328254759311676,
        "validation_diagnostics": {
          "mean_edge_weight": 0.3148790210485458,
          "mean_path_reliability": 0.46587603986263276,
          "mean_reliability_gain": 0.018038900569081306,
          "mean_path_prior_weight": 0.0,
          "mean_path_salience_weight": 0.0,
          "mean_path_context_importance": 0.2290868952870369,
          "mean_path_entropy": 2.602407431602478,
          "mean_path_duplicate_rate": 0.13297526091337203,
          "inference_seconds": 0.41586740012280643,
          "inference_samples_per_second": 2885.5351480920067,
          "top_path_index_pairs": [
            {
              "source_index": 7,
              "bridge_index": -1,
              "target_index": 0,
              "count": 2,
              "mean_weight": 0.1868145763874054,
              "mean_reliability": 0.4653332531452179,
              "mean_edge_weight": 0.28423038125038147,
              "mean_prior_weight": 0.0,
              "mean_salience_weight": 0.0,
              "mean_hop_count": 1.0
            },
            {
              "source_index": 23,
              "bridge_index": -1,
              "target_index": 10,
              "count": 40,
              "mean_weight": 0.18461924530565738,
              "mean_reliability": 0.44552508294582366,
              "mean_edge_weight": 0.29249167665839193,
              "mean_prior_weight": 0.0,
              "mean_salience_weight": 0.0,
              "mean_hop_count": 1.0
            },
            {
              "source_index": 21,
              "bridge_index": -1,
              "target_index": 3,
              "count": 8,
              "mean_weight": 0.17017659358680248,
              "mean_reliability": 0.44743385165929794,
              "mean_edge_weight": 0.28823669254779816,
              "mean_prior_weight": 0.0,
              "mean_salience_weight": 0.0,
              "mean_hop_count": 1.0
            },
            {
              "source_index": 5,
              "bridge_index": -1,
              "target_index": 6,
              "count": 7,
              "mean_weight": 0.16735140340668814,
              "mean_reliability": 0.4513191282749176,
              "mean_edge_weight": 0.29883386407579693,
              "mean_prior_weight": 0.0,
              "mean_salience_weight": 0.0,
              "mean_hop_count": 1.0
            },
            {
              "source_index": 23,
              "bridge_index": -1,
              "target_index": 22,
              "count": 4,
              "mean_weight": 0.16448325663805008,
              "mean_reliability": 0.44818949699401855,
              "mean_edge_weight": 0.29653431475162506,
              "mean_prior_weight": 0.0,
              "mean_salience_weight": 0.0,
              "mean_hop_count": 1.0
            },
            {
              "source_index": 9,
              "bridge_index": -1,
              "target_index": 19,
              "count": 1,
              "mean_weight": 0.16148635745048523,
              "mean_reliability": 0.4289112687110901,
              "mean_edge_weight": 0.27783292531967163,
              "mean_prior_weight": 0.0,
              "mean_salience_weight": 0.0,
              "mean_hop_count": 1.0
            },
            {
              "source_index": 17,
              "bridge_index": -1,
              "target_index": 19,
              "count": 11,
              "mean_weight": 0.15342758562077174,
              "mean_reliability": 0.45625600489703094,
              "mean_edge_weight": 0.2928233580155806,
              "mean_prior_weight": 0.0,
              "mean_salience_weight": 0.0,
              "mean_hop_count": 1.0
            },
            {
              "source_index": 23,
              "bridge_index": -1,
              "target_index": 5,
              "count": 1,
              "mean_weight": 0.14996129274368286,
              "mean_reliability": 0.46049338579177856,
              "mean_edge_weight": 0.27597591280937195,
              "mean_prior_weight": 0.0,
              "mean_salience_weight": 0.0,
              "mean_hop_count": 1.0
            },
            {
              "source_index": 5,
              "bridge_index": -1,
              "target_index": 19,
              "count": 61,
              "mean_weight": 0.14845042901693797,
              "mean_reliability": 0.4642587328543428,
              "mean_edge_weight": 0.30302479765454277,
              "mean_prior_weight": 0.0,
              "mean_salience_weight": 0.0,
              "mean_hop_count": 1.0
            },
            {
              "source_index": 15,
              "bridge_index": -1,
              "target_index": 14,
              "count": 49,
              "mean_weight": 0.1464817067798303,
              "mean_reliability": 0.4673012452466147,
              "mean_edge_weight": 0.2831392038841637,
              "mean_prior_weight": 0.0,
              "mean_salience_weight": 0.0,
              "mean_hop_count": 1.0
            },
            {
              "source_index": 20,
              "bridge_index": -1,
              "target_index": 10,
              "count": 7,
              "mean_weight": 0.13998376258781978,
              "mean_reliability": 0.4997993750231607,
              "mean_edge_weight": 0.2858065792492458,
              "mean_prior_weight": 0.0,
              "mean_salience_weight": 0.0,
              "mean_hop_count": 1.0
            },
            {
              "source_index": 2,
              "bridge_index": -1,
              "target_index": 11,
              "count": 1,
              "mean_weight": 0.13367527723312378,
              "mean_reliability": 0.4230039417743683,
              "mean_edge_weight": 0.2877809405326843,
              "mean_prior_weight": 0.0,
              "mean_salience_weight": 0.0,
              "mean_hop_count": 1.0
            },
            {
              "source_index": 9,
              "bridge_index": -1,
              "target_index": 21,
              "count": 4,
              "mean_weight": 0.1335035376250744,
              "mean_reliability": 0.4546225368976593,
              "mean_edge_weight": 0.28929027915000916,
              "mean_prior_weight": 0.0,
              "mean_salience_weight": 0.0,
              "mean_hop_count": 1.0
            },
            {
              "source_index": 8,
              "bridge_index": -1,
              "target_index": 4,
              "count": 3,
              "mean_weight": 0.13018445670604706,
              "mean_reliability": 0.44821008046468097,
              "mean_edge_weight": 0.278627614180247,
              "mean_prior_weight": 0.0,
              "mean_salience_weight": 0.0,
              "mean_hop_count": 1.0
            },
            {
              "source_index": 23,
              "bridge_index": -1,
              "target_index": 9,
              "count": 11,
              "mean_weight": 0.12957008826461705,
              "mean_reliability": 0.45578869635408575,
              "mean_edge_weight": 0.2878895483233712,
              "mean_prior_weight": 0.0,
              "mean_salience_weight": 0.0,
              "mean_hop_count": 1.0
            },
            {
              "source_index": 20,
              "bridge_index": -1,
              "target_index": 9,
              "count": 130,
              "mean_weight": 0.1290314512470594,
              "mean_reliability": 0.4705965214050733,
              "mean_edge_weight": 0.2923456512964689,
              "mean_prior_weight": 0.0,
              "mean_salience_weight": 0.0,
              "mean_hop_count": 1.0
            },
            {
              "source_index": 23,
              "bridge_index": -1,
              "target_index": 16,
              "count": 2,
              "mean_weight": 0.12828925997018814,
              "mean_reliability": 0.44924259185791016,
              "mean_edge_weight": 0.30274342000484467,
              "mean_prior_weight": 0.0,
              "mean_salience_weight": 0.0,
              "mean_hop_count": 1.0
            },
            {
              "source_index": 5,
              "bridge_index": -1,
              "target_index": 13,
              "count": 73,
              "mean_weight": 0.1266707436577098,
              "mean_reliability": 0.4530145178918969,
              "mean_edge_weight": 0.2972320930598533,
              "mean_prior_weight": 0.0,
              "mean_salience_weight": 0.0,
              "mean_hop_count": 1.0
            },
            {
              "source_index": 10,
              "bridge_index": -1,
              "target_index": 11,
              "count": 743,
              "mean_weight": 0.12644586891868473,
              "mean_reliability": 0.42442024030884373,
              "mean_edge_weight": 0.36062976348929576,
              "mean_prior_weight": 0.0,
              "mean_salience_weight": 0.0,
              "mean_hop_count": 1.0
            },
            {
              "source_index": 8,
              "bridge_index": -1,
              "target_index": 3,
              "count": 7,
              "mean_weight": 0.12552713922091893,
              "mean_reliability": 0.44402672137532917,
              "mean_edge_weight": 0.2984393196446555,
              "mean_prior_weight": 0.0,
              "mean_salience_weight": 0.0,
              "mean_hop_count": 1.0
            },
            {
              "source_index": 5,
              "bridge_index": -1,
              "target_index": 8,
              "count": 525,
              "mean_weight": 0.12499056944357498,
              "mean_reliability": 0.4895382324854533,
              "mean_edge_weight": 0.33638981887272423,
              "mean_prior_weight": 0.0,
              "mean_salience_weight": 0.0,
              "mean_hop_count": 1.0
            },
            {
              "source_index": 4,
              "bridge_index": -1,
              "target_index": 21,
              "count": 121,
              "mean_weight": 0.1239762340233592,
              "mean_reliability": 0.45431248141714364,
              "mean_edge_weight": 0.32159020733242194,
              "mean_prior_weight": 0.0,
              "mean_salience_weight": 0.0,
              "mean_hop_count": 1.0
            },
            {
              "source_index": 21,
              "bridge_index": -1,
              "target_index": 14,
              "count": 23,
              "mean_weight": 0.1239418115304864,
              "mean_reliability": 0.465362223594085,
              "mean_edge_weight": 0.29611588561016583,
              "mean_prior_weight": 0.0,
              "mean_salience_weight": 0.0,
              "mean_hop_count": 1.0
            },
            {
              "source_index": 24,
              "bridge_index": -1,
              "target_index": 3,
              "count": 2,
              "mean_weight": 0.12346858158707619,
              "mean_reliability": 0.4945458769798279,
              "mean_edge_weight": 0.28123249113559723,
              "mean_prior_weight": 0.0,
              "mean_salience_weight": 0.0,
              "mean_hop_count": 1.0
            },
            {
              "source_index": 7,
              "bridge_index": -1,
              "target_index": 24,
              "count": 1,
              "mean_weight": 0.12295898050069809,
              "mean_reliability": 0.4552663266658783,
              "mean_edge_weight": 0.2731128931045532,
              "mean_prior_weight": 0.0,
              "mean_salience_weight": 0.0,
              "mean_hop_count": 1.0
            },
            {
              "source_index": 15,
              "bridge_index": -1,
              "target_index": 19,
              "count": 46,
              "mean_weight": 0.12281780779037786,
              "mean_reliability": 0.4516569991474566,
              "mean_edge_weight": 0.2936582720797995,
              "mean_prior_weight": 0.0,
              "mean_salience_weight": 0.0,
              "mean_hop_count": 1.0
            },
            {
              "source_index": 2,
              "bridge_index": -1,
              "target_index": 3,
              "count": 2,
              "mean_weight": 0.120396688580513,
              "mean_reliability": 0.48291581869125366,
              "mean_edge_weight": 0.2876030206680298,
              "mean_prior_weight": 0.0,
              "mean_salience_weight": 0.0,
              "mean_hop_count": 1.0
            },
            {
              "source_index": 8,
              "bridge_index": -1,
              "target_index": 5,
              "count": 1,
              "mean_weight": 0.12013503909111023,
              "mean_reliability": 0.4533535838127136,
              "mean_edge_weight": 0.28392502665519714,
              "mean_prior_weight": 0.0,
              "mean_salience_weight": 0.0,
              "mean_hop_count": 1.0
            },
            {
              "source_index": 16,
              "bridge_index": -1,
              "target_index": 21,
              "count": 2,
              "mean_weight": 0.12012093141674995,
              "mean_reliability": 0.4747556000947952,
              "mean_edge_weight": 0.27908894419670105,
              "mean_prior_weight": 0.0,
              "mean_salience_weight": 0.0,
              "mean_hop_count": 1.0
            },
            {
              "source_index": 16,
              "bridge_index": -1,
              "target_index": 5,
              "count": 110,
              "mean_weight": 0.12001239935105497,
              "mean_reliability": 0.4673961032520641,
              "mean_edge_weight": 0.3081722264940088,
              "mean_prior_weight": 0.0,
              "mean_salience_weight": 0.0,
              "mean_hop_count": 1.0
            },
            {
              "source_index": 15,
              "bridge_index": -1,
              "target_index": 4,
              "count": 4,
              "mean_weight": 0.11892385967075825,
              "mean_reliability": 0.45416270941495895,
              "mean_edge_weight": 0.29376640170812607,
              "mean_prior_weight": 0.0,
              "mean_salience_weight": 0.0,
              "mean_hop_count": 1.0
            },
            {
              "source_index": 24,
              "bridge_index": -1,
              "target_index": 14,
              "count": 3,
              "mean_weight": 0.1175826092561086,
              "mean_reliability": 0.4384352167447408,
              "mean_edge_weight": 0.2940641442934672,
              "mean_prior_weight": 0.0,
              "mean_salience_weight": 0.0,
              "mean_hop_count": 1.0
            },
            {
              "source_index": 24,
              "bridge_index": -1,
              "target_index": 22,
              "count": 16,
              "mean_weight": 0.11661711928900331,
              "mean_reliability": 0.44848037883639336,
              "mean_edge_weight": 0.2869523633271456,
              "mean_prior_weight": 0.0,
              "mean_salience_weight": 0.0,
              "mean_hop_count": 1.0
            },
            {
              "source_index": 17,
              "bridge_index": -1,
              "target_index": 5,
              "count": 49,
              "mean_weight": 0.11655351595610988,
              "mean_reliability": 0.476415148803166,
              "mean_edge_weight": 0.29642279111609166,
              "mean_prior_weight": 0.0,
              "mean_salience_weight": 0.0,
              "mean_hop_count": 1.0
            },
            {
              "source_index": 20,
              "bridge_index": -1,
              "target_index": 11,
              "count": 9,
              "mean_weight": 0.1151632269223531,
              "mean_reliability": 0.4584634270932939,
              "mean_edge_weight": 0.28163014517890084,
              "mean_prior_weight": 0.0,
              "mean_salience_weight": 0.0,
              "mean_hop_count": 1.0
            },
            {
              "source_index": 24,
              "bridge_index": -1,
              "target_index": 10,
              "count": 2,
              "mean_weight": 0.11432349868118763,
              "mean_reliability": 0.44526417553424835,
              "mean_edge_weight": 0.30040909349918365,
              "mean_prior_weight": 0.0,
              "mean_salience_weight": 0.0,
              "mean_hop_count": 1.0
            },
            {
              "source_index": 24,
              "bridge_index": -1,
              "target_index": 19,
              "count": 5,
              "mean_weight": 0.11306029260158539,
              "mean_reliability": 0.4422278106212616,
              "mean_edge_weight": 0.29237709045410154,
              "mean_prior_weight": 0.0,
              "mean_salience_weight": 0.0,
              "mean_hop_count": 1.0
            },
            {
              "source_index": 10,
              "bridge_index": -1,
              "target_index": 5,
              "count": 1,
              "mean_weight": 0.11076543480157852,
              "mean_reliability": 0.4440218508243561,
              "mean_edge_weight": 0.2964627146720886,
              "mean_prior_weight": 0.0,
              "mean_salience_weight": 0.0,
              "mean_hop_count": 1.0
            },
            {
              "source_index": 5,
              "bridge_index": -1,
              "target_index": 23,
              "count": 37,
              "mean_weight": 0.10999797868567544,
              "mean_reliability": 0.45172339113982946,
              "mean_edge_weight": 0.31429019328710195,
              "mean_prior_weight": 0.0,
              "mean_salience_weight": 0.0,
              "mean_hop_count": 1.0
            },
            {
              "source_index": 15,
              "bridge_index": -1,
              "target_index": 5,
              "count": 95,
              "mean_weight": 0.10984112253706706,
              "mean_reliability": 0.46792759644357784,
              "mean_edge_weight": 0.31156418323516843,
              "mean_prior_weight": 0.0,
              "mean_salience_weight": 0.0,
              "mean_hop_count": 1.0
            },
            {
              "source_index": 21,
              "bridge_index": -1,
              "target_index": 10,
              "count": 4,
              "mean_weight": 0.10983278416097164,
              "mean_reliability": 0.47021880000829697,
              "mean_edge_weight": 0.28940449655056,
              "mean_prior_weight": 0.0,
              "mean_salience_weight": 0.0,
              "mean_hop_count": 1.0
            },
            {
              "source_index": 16,
              "bridge_index": -1,
              "target_index": 24,
              "count": 157,
              "mean_weight": 0.10871357381770945,
              "mean_reliability": 0.4756176194567589,
              "mean_edge_weight": 0.3000321872295088,
              "mean_prior_weight": 0.0,
              "mean_salience_weight": 0.0,
              "mean_hop_count": 1.0
            },
            {
              "source_index": 7,
              "bridge_index": -1,
              "target_index": 4,
              "count": 7,
              "mean_weight": 0.10867321384804589,
              "mean_reliability": 0.524178568805967,
              "mean_edge_weight": 0.2921111583709717,
              "mean_prior_weight": 0.0,
              "mean_salience_weight": 0.0,
              "mean_hop_count": 1.0
            },
            {
              "source_index": 2,
              "bridge_index": -1,
              "target_index": 5,
              "count": 3,
              "mean_weight": 0.10833545277516048,
              "mean_reliability": 0.47057655453681946,
              "mean_edge_weight": 0.28259148200352985,
              "mean_prior_weight": 0.0,
              "mean_salience_weight": 0.0,
              "mean_hop_count": 1.0
            },
            {
              "source_index": 5,
              "bridge_index": -1,
              "target_index": 10,
              "count": 47,
              "mean_weight": 0.10754149724194344,
              "mean_reliability": 0.4889624106123092,
              "mean_edge_weight": 0.3069648615857388,
              "mean_prior_weight": 0.0,
              "mean_salience_weight": 0.0,
              "mean_hop_count": 1.0
            },
            {
              "source_index": 4,
              "bridge_index": -1,
              "target_index": 7,
              "count": 5,
              "mean_weight": 0.10746601819992066,
              "mean_reliability": 0.47508904337882996,
              "mean_edge_weight": 0.2939850687980652,
              "mean_prior_weight": 0.0,
              "mean_salience_weight": 0.0,
              "mean_hop_count": 1.0
            },
            {
              "source_index": 5,
              "bridge_index": -1,
              "target_index": 24,
              "count": 17,
              "mean_weight": 0.1068289048750611,
              "mean_reliability": 0.46597516712020426,
              "mean_edge_weight": 0.2855245769023895,
              "mean_prior_weight": 0.0,
              "mean_salience_weight": 0.0,
              "mean_hop_count": 1.0
            },
            {
              "source_index": 7,
              "bridge_index": -1,
              "target_index": 22,
              "count": 10,
              "mean_weight": 0.10641092136502266,
              "mean_reliability": 0.4982160270214081,
              "mean_edge_weight": 0.2892066419124603,
              "mean_prior_weight": 0.0,
              "mean_salience_weight": 0.0,
              "mean_hop_count": 1.0
            },
            {
              "source_index": 6,
              "bridge_index": -1,
              "target_index": 10,
              "count": 3,
              "mean_weight": 0.10566374411185582,
              "mean_reliability": 0.45089662075042725,
              "mean_edge_weight": 0.3121693432331085,
              "mean_prior_weight": 0.0,
              "mean_salience_weight": 0.0,
              "mean_hop_count": 1.0
            },
            {
              "source_index": 8,
              "bridge_index": -1,
              "target_index": 9,
              "count": 2,
              "mean_weight": 0.10490784049034119,
              "mean_reliability": 0.4588686376810074,
              "mean_edge_weight": 0.2762961685657501,
              "mean_prior_weight": 0.0,
              "mean_salience_weight": 0.0,
              "mean_hop_count": 1.0
            }
          ]
        },
        "test_diagnostics": {
          "mean_edge_weight": 0.31374394297599795,
          "mean_path_reliability": 0.4662051200866699,
          "mean_reliability_gain": 0.018038900569081306,
          "mean_path_prior_weight": 0.0,
          "mean_path_salience_weight": 0.0,
          "mean_path_context_importance": 0.23347448706626892,
          "mean_path_entropy": 2.6024948358535767,
          "mean_path_duplicate_rate": 0.13028971403837203,
          "inference_seconds": 0.4121208998840302,
          "inference_samples_per_second": 2911.766911936951,
          "top_path_index_pairs": [
            {
              "source_index": 9,
              "bridge_index": -1,
              "target_index": 19,
              "count": 3,
              "mean_weight": 0.18262328207492828,
              "mean_reliability": 0.4526263276735942,
              "mean_edge_weight": 0.2800520559151967,
              "mean_prior_weight": 0.0,
              "mean_salience_weight": 0.0,
              "mean_hop_count": 1.0
            },
            {
              "source_index": 23,
              "bridge_index": -1,
              "target_index": 10,
              "count": 44,
              "mean_weight": 0.17825613949786534,
              "mean_reliability": 0.4455712308937853,
              "mean_edge_weight": 0.2906307117505507,
              "mean_prior_weight": 0.0,
              "mean_salience_weight": 0.0,
              "mean_hop_count": 1.0
            },
            {
              "source_index": 9,
              "bridge_index": -1,
              "target_index": 5,
              "count": 3,
              "mean_weight": 0.1711154282093048,
              "mean_reliability": 0.5141777197519938,
              "mean_edge_weight": 0.27800490458806354,
              "mean_prior_weight": 0.0,
              "mean_salience_weight": 0.0,
              "mean_hop_count": 1.0
            },
            {
              "source_index": 21,
              "bridge_index": -1,
              "target_index": 3,
              "count": 6,
              "mean_weight": 0.17068123817443848,
              "mean_reliability": 0.44935692350069684,
              "mean_edge_weight": 0.2913238803545634,
              "mean_prior_weight": 0.0,
              "mean_salience_weight": 0.0,
              "mean_hop_count": 1.0
            },
            {
              "source_index": 23,
              "bridge_index": -1,
              "target_index": 9,
              "count": 5,
              "mean_weight": 0.16684336066246033,
              "mean_reliability": 0.4605145394802094,
              "mean_edge_weight": 0.2850085198879242,
              "mean_prior_weight": 0.0,
              "mean_salience_weight": 0.0,
              "mean_hop_count": 1.0
            },
            {
              "source_index": 5,
              "bridge_index": -1,
              "target_index": 6,
              "count": 6,
              "mean_weight": 0.16567096362511316,
              "mean_reliability": 0.45753232141335803,
              "mean_edge_weight": 0.29410530130068463,
              "mean_prior_weight": 0.0,
              "mean_salience_weight": 0.0,
              "mean_hop_count": 1.0
            },
            {
              "source_index": 23,
              "bridge_index": -1,
              "target_index": 5,
              "count": 2,
              "mean_weight": 0.16064967215061188,
              "mean_reliability": 0.45275481045246124,
              "mean_edge_weight": 0.2951347976922989,
              "mean_prior_weight": 0.0,
              "mean_salience_weight": 0.0,
              "mean_hop_count": 1.0
            },
            {
              "source_index": 17,
              "bridge_index": -1,
              "target_index": 19,
              "count": 24,
              "mean_weight": 0.15906824745858708,
              "mean_reliability": 0.4604141252736251,
              "mean_edge_weight": 0.2976248028377692,
              "mean_prior_weight": 0.0,
              "mean_salience_weight": 0.0,
              "mean_hop_count": 1.0
            },
            {
              "source_index": 20,
              "bridge_index": -1,
              "target_index": 1,
              "count": 2,
              "mean_weight": 0.15677735209465027,
              "mean_reliability": 0.459836944937706,
              "mean_edge_weight": 0.2785436064004898,
              "mean_prior_weight": 0.0,
              "mean_salience_weight": 0.0,
              "mean_hop_count": 1.0
            },
            {
              "source_index": 7,
              "bridge_index": -1,
              "target_index": 0,
              "count": 1,
              "mean_weight": 0.15427540242671967,
              "mean_reliability": 0.47412818670272827,
              "mean_edge_weight": 0.28642722964286804,
              "mean_prior_weight": 0.0,
              "mean_salience_weight": 0.0,
              "mean_hop_count": 1.0
            },
            {
              "source_index": 17,
              "bridge_index": -1,
              "target_index": 14,
              "count": 1,
              "mean_weight": 0.15354792773723602,
              "mean_reliability": 0.4335719645023346,
              "mean_edge_weight": 0.2804235816001892,
              "mean_prior_weight": 0.0,
              "mean_salience_weight": 0.0,
              "mean_hop_count": 1.0
            },
            {
              "source_index": 2,
              "bridge_index": -1,
              "target_index": 11,
              "count": 2,
              "mean_weight": 0.15051710605621338,
              "mean_reliability": 0.4270080626010895,
              "mean_edge_weight": 0.27838510274887085,
              "mean_prior_weight": 0.0,
              "mean_salience_weight": 0.0,
              "mean_hop_count": 1.0
            },
            {
              "source_index": 5,
              "bridge_index": -1,
              "target_index": 19,
              "count": 65,
              "mean_weight": 0.14887185606818934,
              "mean_reliability": 0.46516613272520213,
              "mean_edge_weight": 0.2984238106470842,
              "mean_prior_weight": 0.0,
              "mean_salience_weight": 0.0,
              "mean_hop_count": 1.0
            },
            {
              "source_index": 15,
              "bridge_index": -1,
              "target_index": 14,
              "count": 41,
              "mean_weight": 0.14342841396971448,
              "mean_reliability": 0.46675488352775574,
              "mean_edge_weight": 0.28178669475927587,
              "mean_prior_weight": 0.0,
              "mean_salience_weight": 0.0,
              "mean_hop_count": 1.0
            },
            {
              "source_index": 23,
              "bridge_index": -1,
              "target_index": 22,
              "count": 3,
              "mean_weight": 0.14150024205446243,
              "mean_reliability": 0.46407904227574664,
              "mean_edge_weight": 0.2892336845397949,
              "mean_prior_weight": 0.0,
              "mean_salience_weight": 0.0,
              "mean_hop_count": 1.0
            },
            {
              "source_index": 8,
              "bridge_index": -1,
              "target_index": 4,
              "count": 2,
              "mean_weight": 0.1397825889289379,
              "mean_reliability": 0.44882941246032715,
              "mean_edge_weight": 0.2745770514011383,
              "mean_prior_weight": 0.0,
              "mean_salience_weight": 0.0,
              "mean_hop_count": 1.0
            },
            {
              "source_index": 24,
              "bridge_index": -1,
              "target_index": 3,
              "count": 3,
              "mean_weight": 0.1366856520374616,
              "mean_reliability": 0.4843027393023173,
              "mean_edge_weight": 0.27746695280075073,
              "mean_prior_weight": 0.0,
              "mean_salience_weight": 0.0,
              "mean_hop_count": 1.0
            },
            {
              "source_index": 23,
              "bridge_index": -1,
              "target_index": 21,
              "count": 3,
              "mean_weight": 0.13642310599486032,
              "mean_reliability": 0.45872921744982403,
              "mean_edge_weight": 0.28797751665115356,
              "mean_prior_weight": 0.0,
              "mean_salience_weight": 0.0,
              "mean_hop_count": 1.0
            },
            {
              "source_index": 8,
              "bridge_index": -1,
              "target_index": 5,
              "count": 1,
              "mean_weight": 0.13592903316020966,
              "mean_reliability": 0.4704394042491913,
              "mean_edge_weight": 0.28705915808677673,
              "mean_prior_weight": 0.0,
              "mean_salience_weight": 0.0,
              "mean_hop_count": 1.0
            },
            {
              "source_index": 20,
              "bridge_index": -1,
              "target_index": 9,
              "count": 119,
              "mean_weight": 0.13138423601807164,
              "mean_reliability": 0.46802740011896404,
              "mean_edge_weight": 0.29183554849704774,
              "mean_prior_weight": 0.0,
              "mean_salience_weight": 0.0,
              "mean_hop_count": 1.0
            },
            {
              "source_index": 17,
              "bridge_index": -1,
              "target_index": 5,
              "count": 44,
              "mean_weight": 0.13023591778156432,
              "mean_reliability": 0.47280279479243537,
              "mean_edge_weight": 0.29686111211776733,
              "mean_prior_weight": 0.0,
              "mean_salience_weight": 0.0,
              "mean_hop_count": 1.0
            },
            {
              "source_index": 5,
              "bridge_index": -1,
              "target_index": 13,
              "count": 105,
              "mean_weight": 0.12903131047884622,
              "mean_reliability": 0.4528532522065299,
              "mean_edge_weight": 0.2993235142458053,
              "mean_prior_weight": 0.0,
              "mean_salience_weight": 0.0,
              "mean_hop_count": 1.0
            },
            {
              "source_index": 21,
              "bridge_index": -1,
              "target_index": 10,
              "count": 8,
              "mean_weight": 0.12870651297271252,
              "mean_reliability": 0.46723540499806404,
              "mean_edge_weight": 0.2894414961338043,
              "mean_prior_weight": 0.0,
              "mean_salience_weight": 0.0,
              "mean_hop_count": 1.0
            },
            {
              "source_index": 19,
              "bridge_index": -1,
              "target_index": 6,
              "count": 2,
              "mean_weight": 0.1281094327569008,
              "mean_reliability": 0.4755539000034332,
              "mean_edge_weight": 0.2883974462747574,
              "mean_prior_weight": 0.0,
              "mean_salience_weight": 0.0,
              "mean_hop_count": 1.0
            },
            {
              "source_index": 21,
              "bridge_index": -1,
              "target_index": 14,
              "count": 31,
              "mean_weight": 0.12785717700758287,
              "mean_reliability": 0.4692072522255682,
              "mean_edge_weight": 0.29799175550860746,
              "mean_prior_weight": 0.0,
              "mean_salience_weight": 0.0,
              "mean_hop_count": 1.0
            },
            {
              "source_index": 10,
              "bridge_index": -1,
              "target_index": 11,
              "count": 645,
              "mean_weight": 0.12612573686380718,
              "mean_reliability": 0.42437571836996446,
              "mean_edge_weight": 0.3595380651858426,
              "mean_prior_weight": 0.0,
              "mean_salience_weight": 0.0,
              "mean_hop_count": 1.0
            },
            {
              "source_index": 9,
              "bridge_index": -1,
              "target_index": 21,
              "count": 5,
              "mean_weight": 0.1250126466155052,
              "mean_reliability": 0.44425161480903624,
              "mean_edge_weight": 0.2927680671215057,
              "mean_prior_weight": 0.0,
              "mean_salience_weight": 0.0,
              "mean_hop_count": 1.0
            },
            {
              "source_index": 20,
              "bridge_index": -1,
              "target_index": 10,
              "count": 7,
              "mean_weight": 0.12198055961302348,
              "mean_reliability": 0.4980458617210388,
              "mean_edge_weight": 0.2818237372807094,
              "mean_prior_weight": 0.0,
              "mean_salience_weight": 0.0,
              "mean_hop_count": 1.0
            },
            {
              "source_index": 20,
              "bridge_index": -1,
              "target_index": 11,
              "count": 14,
              "mean_weight": 0.12074625066348485,
              "mean_reliability": 0.4698778007711683,
              "mean_edge_weight": 0.2818963421242578,
              "mean_prior_weight": 0.0,
              "mean_salience_weight": 0.0,
              "mean_hop_count": 1.0
            },
            {
              "source_index": 23,
              "bridge_index": -1,
              "target_index": 16,
              "count": 4,
              "mean_weight": 0.12027810700237751,
              "mean_reliability": 0.4459040239453316,
              "mean_edge_weight": 0.2905045673251152,
              "mean_prior_weight": 0.0,
              "mean_salience_weight": 0.0,
              "mean_hop_count": 1.0
            },
            {
              "source_index": 5,
              "bridge_index": -1,
              "target_index": 8,
              "count": 575,
              "mean_weight": 0.11998678387507149,
              "mean_reliability": 0.4893504230354143,
              "mean_edge_weight": 0.3400824933466704,
              "mean_prior_weight": 0.0,
              "mean_salience_weight": 0.0,
              "mean_hop_count": 1.0
            },
            {
              "source_index": 16,
              "bridge_index": -1,
              "target_index": 5,
              "count": 110,
              "mean_weight": 0.11812289384278384,
              "mean_reliability": 0.46752976693890314,
              "mean_edge_weight": 0.30239749144424094,
              "mean_prior_weight": 0.0,
              "mean_salience_weight": 0.0,
              "mean_hop_count": 1.0
            },
            {
              "source_index": 23,
              "bridge_index": -1,
              "target_index": 1,
              "count": 3,
              "mean_weight": 0.11808458715677261,
              "mean_reliability": 0.4957949022452037,
              "mean_edge_weight": 0.2824240227540334,
              "mean_prior_weight": 0.0,
              "mean_salience_weight": 0.0,
              "mean_hop_count": 1.0
            },
            {
              "source_index": 15,
              "bridge_index": -1,
              "target_index": 5,
              "count": 81,
              "mean_weight": 0.11622324043218,
              "mean_reliability": 0.47197357923896227,
              "mean_edge_weight": 0.31530979496461375,
              "mean_prior_weight": 0.0,
              "mean_salience_weight": 0.0,
              "mean_hop_count": 1.0
            },
            {
              "source_index": 17,
              "bridge_index": -1,
              "target_index": 8,
              "count": 5,
              "mean_weight": 0.1146690733730793,
              "mean_reliability": 0.4585610806941986,
              "mean_edge_weight": 0.29657543301582334,
              "mean_prior_weight": 0.0,
              "mean_salience_weight": 0.0,
              "mean_hop_count": 1.0
            },
            {
              "source_index": 16,
              "bridge_index": -1,
              "target_index": 21,
              "count": 2,
              "mean_weight": 0.1141727827489376,
              "mean_reliability": 0.47599245607852936,
              "mean_edge_weight": 0.2872438281774521,
              "mean_prior_weight": 0.0,
              "mean_salience_weight": 0.0,
              "mean_hop_count": 1.0
            },
            {
              "source_index": 5,
              "bridge_index": -1,
              "target_index": 23,
              "count": 45,
              "mean_weight": 0.11381034619278378,
              "mean_reliability": 0.4491721318827735,
              "mean_edge_weight": 0.31571626861890156,
              "mean_prior_weight": 0.0,
              "mean_salience_weight": 0.0,
              "mean_hop_count": 1.0
            },
            {
              "source_index": 19,
              "bridge_index": -1,
              "target_index": 10,
              "count": 16,
              "mean_weight": 0.11317906016483903,
              "mean_reliability": 0.4633405562490225,
              "mean_edge_weight": 0.29467130638659,
              "mean_prior_weight": 0.0,
              "mean_salience_weight": 0.0,
              "mean_hop_count": 1.0
            },
            {
              "source_index": 4,
              "bridge_index": -1,
              "target_index": 21,
              "count": 111,
              "mean_weight": 0.11294143492574091,
              "mean_reliability": 0.4555833524948842,
              "mean_edge_weight": 0.3200565125491168,
              "mean_prior_weight": 0.0,
              "mean_salience_weight": 0.0,
              "mean_hop_count": 1.0
            },
            {
              "source_index": 5,
              "bridge_index": -1,
              "target_index": 10,
              "count": 53,
              "mean_weight": 0.11208390107132354,
              "mean_reliability": 0.4839648177038948,
              "mean_edge_weight": 0.2999072147990173,
              "mean_prior_weight": 0.0,
              "mean_salience_weight": 0.0,
              "mean_hop_count": 1.0
            },
            {
              "source_index": 8,
              "bridge_index": -1,
              "target_index": 3,
              "count": 7,
              "mean_weight": 0.11203499457665853,
              "mean_reliability": 0.4519944744450705,
              "mean_edge_weight": 0.2887108623981476,
              "mean_prior_weight": 0.0,
              "mean_salience_weight": 0.0,
              "mean_hop_count": 1.0
            },
            {
              "source_index": 7,
              "bridge_index": -1,
              "target_index": 22,
              "count": 15,
              "mean_weight": 0.11200231413046519,
              "mean_reliability": 0.49800625443458557,
              "mean_edge_weight": 0.2854481339454651,
              "mean_prior_weight": 0.0,
              "mean_salience_weight": 0.0,
              "mean_hop_count": 1.0
            },
            {
              "source_index": 16,
              "bridge_index": -1,
              "target_index": 24,
              "count": 159,
              "mean_weight": 0.11073749889648936,
              "mean_reliability": 0.47478495866247694,
              "mean_edge_weight": 0.29932332751136154,
              "mean_prior_weight": 0.0,
              "mean_salience_weight": 0.0,
              "mean_hop_count": 1.0
            },
            {
              "source_index": 13,
              "bridge_index": -1,
              "target_index": 5,
              "count": 1,
              "mean_weight": 0.1088252067565918,
              "mean_reliability": 0.48573869466781616,
              "mean_edge_weight": 0.28055477142333984,
              "mean_prior_weight": 0.0,
              "mean_salience_weight": 0.0,
              "mean_hop_count": 1.0
            },
            {
              "source_index": 24,
              "bridge_index": -1,
              "target_index": 14,
              "count": 2,
              "mean_weight": 0.10835336893796921,
              "mean_reliability": 0.4495867192745209,
              "mean_edge_weight": 0.3039694130420685,
              "mean_prior_weight": 0.0,
              "mean_salience_weight": 0.0,
              "mean_hop_count": 1.0
            },
            {
              "source_index": 5,
              "bridge_index": -1,
              "target_index": 9,
              "count": 16,
              "mean_weight": 0.10712633654475212,
              "mean_reliability": 0.5079176798462868,
              "mean_edge_weight": 0.3149553947150707,
              "mean_prior_weight": 0.0,
              "mean_salience_weight": 0.0,
              "mean_hop_count": 1.0
            },
            {
              "source_index": 6,
              "bridge_index": -1,
              "target_index": 1,
              "count": 50,
              "mean_weight": 0.10676164582371711,
              "mean_reliability": 0.47910197913646696,
              "mean_edge_weight": 0.29355558395385745,
              "mean_prior_weight": 0.0,
              "mean_salience_weight": 0.0,
              "mean_hop_count": 1.0
            },
            {
              "source_index": 24,
              "bridge_index": -1,
              "target_index": 19,
              "count": 5,
              "mean_weight": 0.10518677346408367,
              "mean_reliability": 0.4400879144668579,
              "mean_edge_weight": 0.28970595002174376,
              "mean_prior_weight": 0.0,
              "mean_salience_weight": 0.0,
              "mean_hop_count": 1.0
            },
            {
              "source_index": 1,
              "bridge_index": -1,
              "target_index": 14,
              "count": 19,
              "mean_weight": 0.10419323961985738,
              "mean_reliability": 0.45346484999907644,
              "mean_edge_weight": 0.30051871663645696,
              "mean_prior_weight": 0.0,
              "mean_salience_weight": 0.0,
              "mean_hop_count": 1.0
            },
            {
              "source_index": 5,
              "bridge_index": -1,
              "target_index": 4,
              "count": 103,
              "mean_weight": 0.10337021881804882,
              "mean_reliability": 0.5033616620360069,
              "mean_edge_weight": 0.3134195535507017,
              "mean_prior_weight": 0.0,
              "mean_salience_weight": 0.0,
              "mean_hop_count": 1.0
            }
          ]
        },
        "config": {
          "hidden_dim": 16,
          "scales": [
            3,
            5,
            9
          ],
          "graph_top_k": 4,
          "max_paths": 16,
          "use_graph": true,
          "use_reliability": true,
          "use_path_fusion": true,
          "use_residual_evidence": false,
          "use_temporal_descriptors": false,
          "temporal_descriptor_weight": 0.5,
          "prior_strength": 0.0,
          "path_coverage_mode": "target_group",
          "coverage_dedup_mode": "soft",
          "coverage_redundancy_penalty": 0.05,
          "use_task_salience": false,
          "salience_selection_strength": 0.0,
          "use_multihop_paths": false,
          "multihop_path_fraction": 0.25,
          "use_context_router": true,
          "n_feature_groups": 25,
          "n_path_target_allowed": 0,
          "n_path_source_allowed": 0,
          "n_path_bridge_allowed": 0
        }
      }
    }
  ],
  "summary": {
    "cmapss:degradation_stage_id:full": {
      "n_runs": 1,
      "macro_f1_mean": 0.36030776816999016,
      "macro_f1_std": 0.0,
      "balanced_accuracy_mean": 0.36833333333333335,
      "balanced_accuracy_std": 0.0,
      "test_inference_samples_per_second_mean": 2911.766911936951
    }
  }
}
